.
LICENSE.txt
requirements.txt
setup.cfg
setup.py
/
PyDDNS.egg-info/PKG-INFO
PyDDNS.egg-info/SOURCES.txt
PyDDNS.egg-info/dependency_links.txt
PyDDNS.egg-info/requires.txt
PyDDNS.egg-info/top_level.txt
pyddns/pyddns.py