Metadata-Version: 1.0
Name: PyDDNS
Version: 0.2
Summary: PyDDNS uses Amazon's Route53 as a Dynamic DNS provider for sites with dynamic IP addresses
Home-page: http://bitbucket.org/rubeon/pyddns/
Author: Eric Williams
Author-email: eric@ehw.io
License: MIT
Keywords: AWS EC2 DDNS DynDNS boto
Platform: UNKNOWN
